elena/__init__.py
elena/elena.py
elena/static/css/bootstrap-grid.css
elena/static/css/bootstrap-grid.css.map
elena/static/css/bootstrap-grid.min.css
elena/static/css/bootstrap-grid.min.css.map
elena/static/css/bootstrap-grid.rtl.css
elena/static/css/bootstrap-grid.rtl.css.map
elena/static/css/bootstrap-grid.rtl.min.css
elena/static/css/bootstrap-grid.rtl.min.css.map
elena/static/css/bootstrap-reboot.css
elena/static/css/bootstrap-reboot.css.map
elena/static/css/bootstrap-reboot.min.css
elena/static/css/bootstrap-reboot.min.css.map
elena/static/css/bootstrap-reboot.rtl.css
elena/static/css/bootstrap-reboot.rtl.css.map
elena/static/css/bootstrap-reboot.rtl.min.css
elena/static/css/bootstrap-reboot.rtl.min.css.map
elena/static/css/bootstrap-utilities.css
elena/static/css/bootstrap-utilities.css.map
elena/static/css/bootstrap-utilities.min.css
elena/static/css/bootstrap-utilities.min.css.map
elena/static/css/bootstrap-utilities.rtl.css
elena/static/css/bootstrap-utilities.rtl.css.map
elena/static/css/bootstrap-utilities.rtl.min.css
elena/static/css/bootstrap-utilities.rtl.min.css.map
elena/static/css/bootstrap.css
elena/static/css/bootstrap.css.map
elena/static/css/bootstrap.min.css
elena/static/css/bootstrap.min.css.map
elena/static/css/bootstrap.rtl.css
elena/static/css/bootstrap.rtl.css.map
elena/static/css/bootstrap.rtl.min.css
elena/static/css/bootstrap.rtl.min.css.map
elena/static/js/bootstrap.bundle.js
elena/static/js/bootstrap.bundle.js.map
elena/static/js/bootstrap.bundle.min.js
elena/static/js/bootstrap.bundle.min.js.map
elena/static/js/bootstrap.esm.js
elena/static/js/bootstrap.esm.js.map
elena/static/js/bootstrap.esm.min.js
elena/static/js/bootstrap.esm.min.js.map
elena/static/js/bootstrap.js
elena/static/js/bootstrap.js.map
elena/static/js/bootstrap.min.js
elena/static/js/bootstrap.min.js.map
elena/templates/elena.css
elena/templates/elena.js
elena/templates/elena_top.js
elena/templates/index.html
elena/templates/jsglobals.js
elena/templates/subjs.js
elena_game_engine-0.0.2.dist-info/LICENSE
elena_game_engine-0.0.2.dist-info/METADATA
elena_game_engine-0.0.2.dist-info/WHEEL
elena_game_engine-0.0.2.dist-info/top_level.txt
elena_game_engine-0.0.2.dist-info/RECORD
