Metadata-Version: 2.1
Name: elena-game-engine
Version: 0.0.2
Summary: elena Trivia Webapp Generator
Author: Roman Parise, Georgios Detorakis
Project-URL: Homepage, https://github.com/thejackal360/Elena-Game-Engine
Project-URL: Bug Tracker, https://github.com/thejackal360/Elena-Game-Engine/issues
Classifier: Programming Language :: Python :: 3
Classifier: License :: OSI Approved :: GNU General Public License v3 or later (GPLv3+)
Classifier: Operating System :: OS Independent
Requires-Python: >=3.10
License-File: LICENSE
Requires-Dist: matplotlib ==3.5.1
Requires-Dist: flask ==2.0.0
Requires-Dist: gunicorn ==21.2.0
